chart_to_code/__init__.py
chart_to_code/cli.py
chart_to_code/main_plot.py
chart_to_code/oscillator_plot.py
chart_to_code/rule_engine.py
chart_to_code/serve_vLLM.sh
chart_to_code/stock_rsi_plot.py
chart_to_code/utils.py
chart_to_code/prompts/chart_analysis_system_prompt.md
chart_to_code/prompts/prompt.txt
chart_to_code-0.1.5.dist-info/METADATA
chart_to_code-0.1.5.dist-info/WHEEL
chart_to_code-0.1.5.dist-info/entry_points.txt
chart_to_code-0.1.5.dist-info/licenses/LICENSE
chart_to_code-0.1.5.dist-info/RECORD
