Metadata-Version: 2.4
Name: chart-to-code
Version: 0.1.5
Summary: A self-hosted trading assistant based on a trained vision-language-model and algorithmic trading concepts.
Project-URL: Homepage, https://github.com/Ruby-xantho/chart-to-code
Project-URL: Repository, https://github.com/Ruby-xantho/chart-to-code
Project-URL: Issues, https://github.com/Ruby-xantho/chart-to-code/issues
Project-URL: Documentation, https://github.com/Ruby-xantho/chart-to-code#readme
Author-email: Ahmad Shalaby <ahmad.t.shalaby@gmail.com>
Maintainer-email: Ahmad Shalaby <ahmad.t.shalaby@gmail.com>
License: MIT License
License-File: LICENSE
Classifier: Development Status :: 3 - Alpha
Classifier: Intended Audience :: Financial and Insurance Industry
Classifier: License :: OSI Approved :: MIT License
Classifier: Programming Language :: Python :: 3
Classifier: Programming Language :: Python :: 3.10
Classifier: Programming Language :: Python :: 3.11
Classifier: Programming Language :: Python :: 3.12
Classifier: Topic :: Office/Business :: Financial :: Investment
Classifier: Topic :: Scientific/Engineering :: Artificial Intelligence
Requires-Python: >=3.10
Requires-Dist: ccxt
Requires-Dist: matplotlib
Requires-Dist: mplfinance
Requires-Dist: numpy
Requires-Dist: openai
Requires-Dist: pandas
Requires-Dist: pyarrow
Requires-Dist: streamlit-autorefresh
Requires-Dist: streamlit==1.48.1
Provides-Extra: dev
Requires-Dist: black; extra == 'dev'
Requires-Dist: flake8; extra == 'dev'
Requires-Dist: mypy; extra == 'dev'
Requires-Dist: pytest; extra == 'dev'
Requires-Dist: pytest-cov; extra == 'dev'
Provides-Extra: extras
Requires-Dist: pillow; extra == 'extras'
Requires-Dist: python-dotenv; extra == 'extras'
Provides-Extra: gpu
Requires-Dist: accelerate==1.6.0; extra == 'gpu'
Requires-Dist: autoawq==0.2.9; extra == 'gpu'
Requires-Dist: build==1.2.2.post1; extra == 'gpu'
Requires-Dist: cachetools==5.5.2; extra == 'gpu'
Requires-Dist: langchain-community==0.3.24; extra == 'gpu'
Requires-Dist: langchain==0.3.25; extra == 'gpu'
Requires-Dist: openpyxl==3.1.5; extra == 'gpu'
Requires-Dist: optimum==1.25.3; extra == 'gpu'
Requires-Dist: pillow==11.2.1; extra == 'gpu'
Requires-Dist: pypdf4==1.27.0; extra == 'gpu'
Requires-Dist: qwen-vl-utils==0.0.8; extra == 'gpu'
Requires-Dist: tiktoken==0.9.0; extra == 'gpu'
Requires-Dist: torch==2.6.0; extra == 'gpu'
Requires-Dist: torchaudio==2.6.0; extra == 'gpu'
Requires-Dist: torchvision==0.21.0; extra == 'gpu'
Requires-Dist: transformers==4.51.3; extra == 'gpu'
Requires-Dist: triton==3.2.0; extra == 'gpu'
Requires-Dist: typing==3.7.4.3; extra == 'gpu'
Requires-Dist: vllm==0.8.3; extra == 'gpu'
Provides-Extra: trading
Requires-Dist: asyncio-mqtt; extra == 'trading'
Requires-Dist: ccxt; extra == 'trading'
Requires-Dist: python-dotenv; extra == 'trading'
Provides-Extra: training
Requires-Dist: datasets; extra == 'training'
Requires-Dist: evaluate; extra == 'training'
Requires-Dist: jsonlines; extra == 'training'
Requires-Dist: peft; extra == 'training'
Requires-Dist: scikit-learn; extra == 'training'
Requires-Dist: torch; extra == 'training'
Requires-Dist: transformers; extra == 'training'
